webinteractions/__init__.py
webinteractions/http_interaction.py
webinteractions/ip_functions.py
webinteractions/remote_access/__init__.py
webinteractions/remote_access/cgi_script.py
webinteractions/server_client/__init__.py
webinteractions/server_client/tcp_socket_server.py
webinteractions/server_client/udp_socket_server.py
webinteractions/server_client/utils.py
webinteractions/server_client/xmlrpc_wrapper/__init__.py
webinteractions/server_client/xmlrpc_wrapper/client.py
webinteractions/server_client/xmlrpc_wrapper/server.py
webinteractions-0.0.5.dist-info/LICENSE
webinteractions-0.0.5.dist-info/METADATA
webinteractions-0.0.5.dist-info/WHEEL
webinteractions-0.0.5.dist-info/top_level.txt
webinteractions-0.0.5.dist-info/RECORD
